{"page":{"id":"99ce74c8-7dd6-403c-8e4c-285280d90f83_5550","data":{"id":"38c24e89-66b5-4ae3-8921-23f2efe4fe2c","uf":"PE","int":"5540","slug":"agencia-de-ia-em-sao-benedito-do-sul-pe","cidade":"São Benedito do Sul","estado":"Pernambuco","imagem":null,"keywords":"agência de ia em são benedito do sul,inteligencia artificial em são benedito do sul, startflow são benedito do sul, agencia de inteligencia artificial em são benedito do sul, empresa de ia em são benedito do sul, empresa de inteligencia artificial em São Benedito do Sul, automação whatsapp em são benedito do sul, chatbot whatsapp em são benedito do sul, automacao com ia em são benedito do sul, automacao com inteligencia artificial em são benedito do sul","titulo-meta":"Agência de IA em São Benedito do Sul, PE","descricao-meta":"Transforme seu negócio com Inteligência Artificial em São Benedito do Sul e em todo o Brasil","negocios_cidade":"252","negocios_estado":"119.350","populacao_estado":"9.539.029"}}}