{"page":{"id":"99ce74c8-7dd6-403c-8e4c-285280d90f83_2447","data":{"id":"17ce9893-6940-413b-a4e4-aa9fd62251b1","uf":"BA","int":"2440","slug":"agencia-de-ia-em-paratinga-ba","cidade":"Paratinga","estado":"Bahia","imagem":null,"keywords":"agência de ia em paratinga,inteligencia artificial em paratinga, startflow paratinga, agencia de inteligencia artificial em paratinga, empresa de ia em paratinga, empresa de inteligencia artificial em Paratinga, automação whatsapp em paratinga, chatbot whatsapp em paratinga, automacao com ia em paratinga, automacao com inteligencia artificial em paratinga","titulo-meta":"Agência de IA em Paratinga, BA","descricao-meta":"Transforme seu negócio com Inteligência Artificial em Paratinga e em todo o Brasil","negocios_cidade":"913","negocios_estado":"184.683","populacao_estado":"14.850.513"}}}