{"page":{"id":"99ce74c8-7dd6-403c-8e4c-285280d90f83_1909","data":{"id":"6d0a6b68-8dc9-44dc-8bcd-010519572e3f","uf":"MG","int":"1904","slug":"agencia-de-ia-em-juatuba-mg","cidade":"Juatuba","estado":"Minas Gerais","imagem":null,"keywords":"agência de ia em juatuba,inteligencia artificial em juatuba, startflow juatuba, agencia de inteligencia artificial em juatuba, empresa de ia em juatuba, empresa de inteligencia artificial em Juatuba, automação whatsapp em juatuba, chatbot whatsapp em juatuba, automacao com ia em juatuba, automacao com inteligencia artificial em juatuba","titulo-meta":"Agência de IA em Juatuba, MG","descricao-meta":"Transforme seu negócio com Inteligência Artificial em Juatuba e em todo o Brasil","negocios_cidade":"3.407","negocios_estado":"448.949","populacao_estado":"21.322.691"}}}