{"page":{"id":"99ce74c8-7dd6-403c-8e4c-285280d90f83_1846","data":{"id":"976a8717-fa9d-4b28-a829-14104fddb4b4","uf":"PE","int":"1841","slug":"agencia-de-ia-em-sao-joaquim-do-monte-pe","cidade":"São Joaquim do Monte","estado":"Pernambuco","imagem":null,"keywords":"agência de ia em são joaquim do monte,inteligencia artificial em são joaquim do monte, startflow são joaquim do monte, agencia de inteligencia artificial em são joaquim do monte, empresa de ia em são joaquim do monte, empresa de inteligencia artificial em São Joaquim do Monte, automação whatsapp em são joaquim do monte, chatbot whatsapp em são joaquim do monte, automacao com ia em são joaquim do monte, automacao com inteligencia artificial em são joaquim do monte","titulo-meta":"Agência de IA em São Joaquim do Monte, PE","descricao-meta":"Transforme seu negócio com Inteligência Artificial em São Joaquim do Monte e em todo o Brasil","negocios_cidade":"527","negocios_estado":"119.350","populacao_estado":"9.539.029"}}}