{"page":{"id":"99ce74c8-7dd6-403c-8e4c-285280d90f83_4854","data":{"id":"0bd29a80-c15a-463d-8ac0-f07d5d563126","uf":"RS","int":"4843","slug":"agencia-de-ia-em-esteio-rs","cidade":"Esteio","estado":"Rio Grande do Sul","imagem":null,"keywords":"agência de ia em esteio,inteligencia artificial em esteio, startflow esteio, agencia de inteligencia artificial em esteio, empresa de ia em esteio, empresa de inteligencia artificial em Esteio, automação whatsapp em esteio, chatbot whatsapp em esteio, automacao com ia em esteio, automacao com inteligencia artificial em esteio","titulo-meta":"Agência de IA em Esteio, RS","descricao-meta":"Transforme seu negócio com Inteligência Artificial em Esteio e em todo o Brasil","negocios_cidade":"10.714","negocios_estado":"253.069","populacao_estado":"11.422.973"}}}