{"page":{"id":"99ce74c8-7dd6-403c-8e4c-285280d90f83_1309","data":{"id":"7dee1398-6394-4a7f-ba3b-c3281f51d09d","uf":"CE","int":"1304","slug":"agencia-de-ia-em-moraujo-ce","cidade":"Moraújo","estado":"Ceará","imagem":null,"keywords":"agência de ia em moraújo,inteligencia artificial em moraújo, startflow moraújo, agencia de inteligencia artificial em moraújo, empresa de ia em moraújo, empresa de inteligencia artificial em Moraújo, automação whatsapp em moraújo, chatbot whatsapp em moraújo, automacao com ia em moraújo, automacao com inteligencia artificial em moraújo","titulo-meta":"Agência de IA em Moraújo, CE","descricao-meta":"Transforme seu negócio com Inteligência Artificial em Moraújo e em todo o Brasil","negocios_cidade":"336","negocios_estado":"115.206","populacao_estado":"9.233.656"}}}