{"page":{"id":"99ce74c8-7dd6-403c-8e4c-285280d90f83_1569","data":{"id":"f71cd687-ff03-4697-87a0-7f8b2e2cc807","uf":"PB","int":"1564","slug":"agencia-de-ia-em-cruz-do-espirito-santo-pb","cidade":"Cruz do Espírito Santo","estado":"Paraíba","imagem":null,"keywords":"agência de ia em cruz do espírito santo,inteligencia artificial em cruz do espírito santo, startflow cruz do espírito santo, agencia de inteligencia artificial em cruz do espírito santo, empresa de ia em cruz do espírito santo, empresa de inteligencia artificial em Cruz do Espírito Santo, automação whatsapp em cruz do espírito santo, chatbot whatsapp em cruz do espírito santo, automacao com ia em cruz do espírito santo, automacao com inteligencia artificial em cruz do espírito santo","titulo-meta":"Agência de IA em Cruz do Espírito Santo, PB","descricao-meta":"Transforme seu negócio com Inteligência Artificial em Cruz do Espírito Santo e em todo o Brasil","negocios_cidade":"584","negocios_estado":"52.067","populacao_estado":"4.145.040"}}}