{"page":{"id":"99ce74c8-7dd6-403c-8e4c-285280d90f83_74","data":{"id":"b8cbf68c-fc90-4989-be51-d05da042d43d","uf":"GO","int":"72","slug":"agencia-de-ia-em-chapadao-do-ceu-go","cidade":"Chapadão do Céu","estado":"Goiás","imagem":null,"keywords":"agência de ia em chapadão do céu,inteligencia artificial em chapadão do céu, startflow chapadão do céu, agencia de inteligencia artificial em chapadão do céu, empresa de ia em chapadão do céu, empresa de inteligencia artificial em Chapadão do Céu, automação whatsapp em chapadão do céu, chatbot whatsapp em chapadão do céu, automacao com ia em chapadão do céu, automacao com inteligencia artificial em chapadão do céu","titulo-meta":"Agência de IA em Chapadão do Céu, GO","descricao-meta":"Transforme seu negócio com Inteligência Artificial em Chapadão do Céu e em todo o Brasil","negocios_cidade":"1.665","negocios_estado":"171.003","populacao_estado":"7.369.156"}}}