{"page":{"id":"99ce74c8-7dd6-403c-8e4c-285280d90f83_492","data":{"id":"d9228299-b863-4bb1-aea4-2aa239f35233","uf":"PA","int":"490","slug":"agencia-de-ia-em-monte-alegre-pa","cidade":"Monte Alegre","estado":"Pará","imagem":null,"keywords":"agência de ia em monte alegre,inteligencia artificial em monte alegre, startflow monte alegre, agencia de inteligencia artificial em monte alegre, empresa de ia em monte alegre, empresa de inteligencia artificial em Monte Alegre, automação whatsapp em monte alegre, chatbot whatsapp em monte alegre, automacao com ia em monte alegre, automacao com inteligencia artificial em monte alegre","titulo-meta":"Agência de IA em Monte Alegre, PA","descricao-meta":"Transforme seu negócio com Inteligência Artificial em Monte Alegre e em todo o Brasil","negocios_cidade":"2.248","negocios_estado":"81.460","populacao_estado":"8.664.306"}}}