{"page":{"id":"99ce74c8-7dd6-403c-8e4c-285280d90f83_2845","data":{"id":"4992842c-3ff1-458e-ab3f-c4d0a49aef66","uf":"MG","int":"2837","slug":"agencia-de-ia-em-grupiara-mg","cidade":"Grupiara","estado":"Minas Gerais","imagem":null,"keywords":"agência de ia em grupiara,inteligencia artificial em grupiara, startflow grupiara, agencia de inteligencia artificial em grupiara, empresa de ia em grupiara, empresa de inteligencia artificial em Grupiara, automação whatsapp em grupiara, chatbot whatsapp em grupiara, automacao com ia em grupiara, automacao com inteligencia artificial em grupiara","titulo-meta":"Agência de IA em Grupiara, MG","descricao-meta":"Transforme seu negócio com Inteligência Artificial em Grupiara e em todo o Brasil","negocios_cidade":"191","negocios_estado":"448.949","populacao_estado":"21.322.691"}}}