{"page":{"id":"99ce74c8-7dd6-403c-8e4c-285280d90f83_129","data":{"id":"00903482-4cd1-427e-ad19-782c8a59065d","uf":"MT","int":"127","slug":"agencia-de-ia-em-canabrava-do-norte-mt","cidade":"Canabrava do Norte","estado":"Mato Grosso","imagem":null,"keywords":"agência de ia em canabrava do norte,inteligencia artificial em canabrava do norte, startflow canabrava do norte, agencia de inteligencia artificial em canabrava do norte, empresa de ia em canabrava do norte, empresa de inteligencia artificial em Canabrava do Norte, automação whatsapp em canabrava do norte, chatbot whatsapp em canabrava do norte, automacao com ia em canabrava do norte, automacao com inteligencia artificial em canabrava do norte","titulo-meta":"Agência de IA em Canabrava do Norte, MT","descricao-meta":"Transforme seu negócio com Inteligência Artificial em Canabrava do Norte e em todo o Brasil","negocios_cidade":"412","negocios_estado":"93.905","populacao_estado":"3.701.140"}}}