{"page":{"id":"99ce74c8-7dd6-403c-8e4c-285280d90f83_1668","data":{"id":"84932fc3-3433-4922-816a-3108e72f675a","uf":"PB","int":"1663","slug":"agencia-de-ia-em-sao-miguel-de-taipu-pb","cidade":"São Miguel de Taipu","estado":"Paraíba","imagem":null,"keywords":"agência de ia em são miguel de taipu,inteligencia artificial em são miguel de taipu, startflow são miguel de taipu, agencia de inteligencia artificial em são miguel de taipu, empresa de ia em são miguel de taipu, empresa de inteligencia artificial em São Miguel de Taipu, automação whatsapp em são miguel de taipu, chatbot whatsapp em são miguel de taipu, automacao com ia em são miguel de taipu, automacao com inteligencia artificial em são miguel de taipu","titulo-meta":"Agência de IA em São Miguel de Taipu, PB","descricao-meta":"Transforme seu negócio com Inteligência Artificial em São Miguel de Taipu e em todo o Brasil","negocios_cidade":"281","negocios_estado":"52.067","populacao_estado":"4.145.040"}}}