{"page":{"id":"99ce74c8-7dd6-403c-8e4c-285280d90f83_5144","data":{"id":"c76005ba-43b2-4b4f-b394-4c3324086e5d","uf":"MT","int":"5133","slug":"agencia-de-ia-em-nova-brasilandia-mt","cidade":"Nova Brasilândia","estado":"Mato Grosso","imagem":null,"keywords":"agência de ia em nova brasilândia,inteligencia artificial em nova brasilândia, startflow nova brasilândia, agencia de inteligencia artificial em nova brasilândia, empresa de ia em nova brasilândia, empresa de inteligencia artificial em Nova Brasilândia, automação whatsapp em nova brasilândia, chatbot whatsapp em nova brasilândia, automacao com ia em nova brasilândia, automacao com inteligencia artificial em nova brasilândia","titulo-meta":"Agência de IA em Nova Brasilândia, MT","descricao-meta":"Transforme seu negócio com Inteligência Artificial em Nova Brasilândia e em todo o Brasil","negocios_cidade":"407","negocios_estado":"93.905","populacao_estado":"3.701.140"}}}