{"page":{"id":"99ce74c8-7dd6-403c-8e4c-285280d90f83_4981","data":{"id":"1afe4a58-aa84-4f48-ad1b-7a869e9895d5","uf":"MT","int":"4970","slug":"agencia-de-ia-em-curvelandia-mt","cidade":"Curvelândia","estado":"Mato Grosso","imagem":null,"keywords":"agência de ia em curvelândia,inteligencia artificial em curvelândia, startflow curvelândia, agencia de inteligencia artificial em curvelândia, empresa de ia em curvelândia, empresa de inteligencia artificial em Curvelândia, automação whatsapp em curvelândia, chatbot whatsapp em curvelândia, automacao com ia em curvelândia, automacao com inteligencia artificial em curvelândia","titulo-meta":"Agência de IA em Curvelândia, MT","descricao-meta":"Transforme seu negócio com Inteligência Artificial em Curvelândia e em todo o Brasil","negocios_cidade":"453","negocios_estado":"93.905","populacao_estado":"3.701.140"}}}