{"page":{"id":"99ce74c8-7dd6-403c-8e4c-285280d90f83_3890","data":{"id":"fbc7581f-bd26-4c72-813e-0c9bceb30994","uf":"SP","int":"3881","slug":"agencia-de-ia-em-macedonia-sp","cidade":"Macedônia","estado":"São Paulo","imagem":null,"keywords":"agência de ia em macedônia,inteligencia artificial em macedônia, startflow macedônia, agencia de inteligencia artificial em macedônia, empresa de ia em macedônia, empresa de inteligencia artificial em Macedônia, automação whatsapp em macedônia, chatbot whatsapp em macedônia, automacao com ia em macedônia, automacao com inteligencia artificial em macedônia","titulo-meta":"Agência de IA em Macedônia, SP","descricao-meta":"Transforme seu negócio com Inteligência Artificial em Macedônia e em todo o Brasil","negocios_cidade":"1.253","negocios_estado":"1.288.946","populacao_estado":"46.578.256"}}}