{"page":{"id":"99ce74c8-7dd6-403c-8e4c-285280d90f83_3533","data":{"id":"f6f65af6-6cf6-4b81-b199-c94c628da2a2","uf":"RS","int":"3524","slug":"agencia-de-ia-em-mormaco-rs","cidade":"Mormaço","estado":"Rio Grande do Sul","imagem":null,"keywords":"agência de ia em mormaço,inteligencia artificial em mormaço, startflow mormaço, agencia de inteligencia artificial em mormaço, empresa de ia em mormaço, empresa de inteligencia artificial em Mormaço, automação whatsapp em mormaço, chatbot whatsapp em mormaço, automacao com ia em mormaço, automacao com inteligencia artificial em mormaço","titulo-meta":"Agência de IA em Mormaço, RS","descricao-meta":"Transforme seu negócio com Inteligência Artificial em Mormaço e em todo o Brasil","negocios_cidade":"274","negocios_estado":"253.069","populacao_estado":"11.422.973"}}}