{"page":{"id":"99ce74c8-7dd6-403c-8e4c-285280d90f83_400","data":{"id":"1e95664b-3de1-48dd-82d8-531cbe0dd786","uf":"PA","int":"398","slug":"agencia-de-ia-em-acara-pa","cidade":"Acará","estado":"Pará","imagem":null,"keywords":"agência de ia em acará,inteligencia artificial em acará, startflow acará, agencia de inteligencia artificial em acará, empresa de ia em acará, empresa de inteligencia artificial em Acará, automação whatsapp em acará, chatbot whatsapp em acará, automacao com ia em acará, automacao com inteligencia artificial em acará","titulo-meta":"Agência de IA em Acará, PA","descricao-meta":"Transforme seu negócio com Inteligência Artificial em Acará e em todo o Brasil","negocios_cidade":"1.192","negocios_estado":"81.460","populacao_estado":"8.664.306"}}}