{"page":{"id":"99ce74c8-7dd6-403c-8e4c-285280d90f83_5209","data":{"id":"afe70458-da6b-46f2-a860-5c0a96d555da","uf":"MS","int":"5198","slug":"agencia-de-ia-em-miranda-ms","cidade":"Miranda","estado":"Mato Grosso do Sul","imagem":null,"keywords":"agência de ia em miranda,inteligencia artificial em miranda, startflow miranda, agencia de inteligencia artificial em miranda, empresa de ia em miranda, empresa de inteligencia artificial em Miranda, automação whatsapp em miranda, chatbot whatsapp em miranda, automacao com ia em miranda, automacao com inteligencia artificial em miranda","titulo-meta":"Agência de IA em Miranda, MS","descricao-meta":"Transforme seu negócio com Inteligência Artificial em Miranda e em todo o Brasil","negocios_cidade":"1.552","negocios_estado":"55.943","populacao_estado":"2.778.986"}}}