{"page":{"id":"99ce74c8-7dd6-403c-8e4c-285280d90f83_5002","data":{"id":"a2b2d3cc-b8b6-4519-9389-a0666540e381","uf":"RS","int":"4991","slug":"agencia-de-ia-em-humaita-rs","cidade":"Humaitá","estado":"Rio Grande do Sul","imagem":null,"keywords":"agência de ia em humaitá,inteligencia artificial em humaitá, startflow humaitá, agencia de inteligencia artificial em humaitá, empresa de ia em humaitá, empresa de inteligencia artificial em Humaitá, automação whatsapp em humaitá, chatbot whatsapp em humaitá, automacao com ia em humaitá, automacao com inteligencia artificial em humaitá","titulo-meta":"Agência de IA em Humaitá, RS","descricao-meta":"Transforme seu negócio com Inteligência Artificial em Humaitá e em todo o Brasil","negocios_cidade":"512","negocios_estado":"253.069","populacao_estado":"11.422.973"}}}