{"page":{"id":"99ce74c8-7dd6-403c-8e4c-285280d90f83_4717","data":{"id":"f722203d-8ba4-4a10-9268-9770f05835a5","uf":"SC","int":"4706","slug":"agencia-de-ia-em-urubici-sc","cidade":"Urubici","estado":"Santa Catarina","imagem":null,"keywords":"agência de ia em urubici,inteligencia artificial em urubici, startflow urubici, agencia de inteligencia artificial em urubici, empresa de ia em urubici, empresa de inteligencia artificial em Urubici, automação whatsapp em urubici, chatbot whatsapp em urubici, automacao com ia em urubici, automacao com inteligencia artificial em urubici","titulo-meta":"Agência de IA em Urubici, SC","descricao-meta":"Transforme seu negócio com Inteligência Artificial em Urubici e em todo o Brasil","negocios_cidade":"2.103","negocios_estado":"251.482","populacao_estado":"7.252.502"}}}