{"page":{"id":"99ce74c8-7dd6-403c-8e4c-285280d90f83_1923","data":{"id":"e15c17be-2474-4e8b-a83c-da0a00f80e29","uf":"AL","int":"1918","slug":"agencia-de-ia-em-boca-da-mata-al","cidade":"Boca da Mata","estado":"Alagoas","imagem":null,"keywords":"agência de ia em boca da mata,inteligencia artificial em boca da mata, startflow boca da mata, agencia de inteligencia artificial em boca da mata, empresa de ia em boca da mata, empresa de inteligencia artificial em Boca da Mata, automação whatsapp em boca da mata, chatbot whatsapp em boca da mata, automacao com ia em boca da mata, automacao com inteligencia artificial em boca da mata","titulo-meta":"Agência de IA em Boca da Mata, AL","descricao-meta":"Transforme seu negócio com Inteligência Artificial em Boca da Mata e em todo o Brasil","negocios_cidade":"1.172","negocios_estado":"36.561","populacao_estado":"3.220.104"}}}