{"page":{"id":"99ce74c8-7dd6-403c-8e4c-285280d90f83_5472","data":{"id":"b0c38c2c-0579-477f-a0ab-14d91ddc378b","uf":"CE","int":"5461","slug":"agencia-de-ia-em-varjota-ce","cidade":"Varjota","estado":"Ceará","imagem":null,"keywords":"agência de ia em varjota,inteligencia artificial em varjota, startflow varjota, agencia de inteligencia artificial em varjota, empresa de ia em varjota, empresa de inteligencia artificial em Varjota, automação whatsapp em varjota, chatbot whatsapp em varjota, automacao com ia em varjota, automacao com inteligencia artificial em varjota","titulo-meta":"Agência de IA em Varjota, CE","descricao-meta":"Transforme seu negócio com Inteligência Artificial em Varjota e em todo o Brasil","negocios_cidade":"1.366","negocios_estado":"115.206","populacao_estado":"9.233.656"}}}