{"page":{"id":"99ce74c8-7dd6-403c-8e4c-285280d90f83_916","data":{"id":"b5d28182-030d-4221-b525-c81992080400","uf":"MA","int":"912","slug":"agencia-de-ia-em-sao-joao-dos-patos-ma","cidade":"São João dos Patos","estado":"Maranhão","imagem":null,"keywords":"agência de ia em são joão dos patos,inteligencia artificial em são joão dos patos, startflow são joão dos patos, agencia de inteligencia artificial em são joão dos patos, empresa de ia em são joão dos patos, empresa de inteligencia artificial em São João dos Patos, automação whatsapp em são joão dos patos, chatbot whatsapp em são joão dos patos, automacao com ia em são joão dos patos, automacao com inteligencia artificial em são joão dos patos","titulo-meta":"Agência de IA em São João dos Patos, MA","descricao-meta":"Transforme seu negócio com Inteligência Artificial em São João dos Patos e em todo o Brasil","negocios_cidade":"1.277","negocios_estado":"54.104","populacao_estado":"7.010.960"}}}