{"page":{"id":"99ce74c8-7dd6-403c-8e4c-285280d90f83_139","data":{"id":"c0d35b1d-d877-40b0-940d-ae621c7949bb","uf":"MA","int":"137","slug":"agencia-de-ia-em-campestre-do-maranhao-ma","cidade":"Campestre do Maranhão","estado":"Maranhão","imagem":null,"keywords":"agência de ia em campestre do maranhão,inteligencia artificial em campestre do maranhão, startflow campestre do maranhão, agencia de inteligencia artificial em campestre do maranhão, empresa de ia em campestre do maranhão, empresa de inteligencia artificial em Campestre do Maranhão, automação whatsapp em campestre do maranhão, chatbot whatsapp em campestre do maranhão, automacao com ia em campestre do maranhão, automacao com inteligencia artificial em campestre do maranhão","titulo-meta":"Agência de IA em Campestre do Maranhão, MA","descricao-meta":"Transforme seu negócio com Inteligência Artificial em Campestre do Maranhão e em todo o Brasil","negocios_cidade":"522","negocios_estado":"54.104","populacao_estado":"7.010.960"}}}