{"page":{"id":"99ce74c8-7dd6-403c-8e4c-285280d90f83_2504","data":{"id":"801f727d-d8ac-40b0-856c-b65e3e712e98","uf":"BA","int":"2496","slug":"agencia-de-ia-em-sao-sebastiao-do-passe-ba","cidade":"São Sebastião do Passé","estado":"Bahia","imagem":null,"keywords":"agência de ia em são sebastião do passé,inteligencia artificial em são sebastião do passé, startflow são sebastião do passé, agencia de inteligencia artificial em são sebastião do passé, empresa de ia em são sebastião do passé, empresa de inteligencia artificial em São Sebastião do Passé, automação whatsapp em são sebastião do passé, chatbot whatsapp em são sebastião do passé, automacao com ia em são sebastião do passé, automacao com inteligencia artificial em são sebastião do passé","titulo-meta":"Agência de IA em São Sebastião do Passé, BA","descricao-meta":"Transforme seu negócio com Inteligência Artificial em São Sebastião do Passé e em todo o Brasil","negocios_cidade":"2.195","negocios_estado":"184.683","populacao_estado":"14.850.513"}}}