{"page":{"id":"99ce74c8-7dd6-403c-8e4c-285280d90f83_5165","data":{"id":"d563fb26-587a-4903-a567-2d26584645c5","uf":"MT","int":"5154","slug":"agencia-de-ia-em-araguainha-mt","cidade":"Araguainha","estado":"Mato Grosso","imagem":null,"keywords":"agência de ia em araguainha,inteligencia artificial em araguainha, startflow araguainha, agencia de inteligencia artificial em araguainha, empresa de ia em araguainha, empresa de inteligencia artificial em Araguainha, automação whatsapp em araguainha, chatbot whatsapp em araguainha, automacao com ia em araguainha, automacao com inteligencia artificial em araguainha","titulo-meta":"Agência de IA em Araguainha, MT","descricao-meta":"Transforme seu negócio com Inteligência Artificial em Araguainha e em todo o Brasil","negocios_cidade":"232","negocios_estado":"93.905","populacao_estado":"3.701.140"}}}