{"page":{"id":"99ce74c8-7dd6-403c-8e4c-285280d90f83_4495","data":{"id":"a7295d7c-8402-4abe-8bfe-807875641aba","uf":"PR","int":"4484","slug":"agencia-de-ia-em-sertanopolis-pr","cidade":"Sertanópolis","estado":"Paraná","imagem":null,"keywords":"agência de ia em sertanópolis,inteligencia artificial em sertanópolis, startflow sertanópolis, agencia de inteligencia artificial em sertanópolis, empresa de ia em sertanópolis, empresa de inteligencia artificial em Sertanópolis, automação whatsapp em sertanópolis, chatbot whatsapp em sertanópolis, automacao com ia em sertanópolis, automacao com inteligencia artificial em sertanópolis","titulo-meta":"Agência de IA em Sertanópolis, PR","descricao-meta":"Transforme seu negócio com Inteligência Artificial em Sertanópolis e em todo o Brasil","negocios_cidade":"2.543","negocios_estado":"305.103","populacao_estado":"11.660.464"}}}