{"page":{"id":"99ce74c8-7dd6-403c-8e4c-285280d90f83_4716","data":{"id":"740dd507-f908-4a57-8bc9-3d00918ce216","uf":"SC","int":"4705","slug":"agencia-de-ia-em-turvo-sc","cidade":"Turvo","estado":"Santa Catarina","imagem":null,"keywords":"agência de ia em turvo,inteligencia artificial em turvo, startflow turvo, agencia de inteligencia artificial em turvo, empresa de ia em turvo, empresa de inteligencia artificial em Turvo, automação whatsapp em turvo, chatbot whatsapp em turvo, automacao com ia em turvo, automacao com inteligencia artificial em turvo","titulo-meta":"Agência de IA em Turvo, SC","descricao-meta":"Transforme seu negócio com Inteligência Artificial em Turvo e em todo o Brasil","negocios_cidade":"1.981","negocios_estado":"251.482","populacao_estado":"7.252.502"}}}