{"page":{"id":"99ce74c8-7dd6-403c-8e4c-285280d90f83_5333","data":{"id":"3af44cc7-3d54-43f3-a25e-7fee90112415","uf":"GO","int":"5322","slug":"agencia-de-ia-em-firminopolis-go","cidade":"Firminópolis","estado":"Goiás","imagem":null,"keywords":"agência de ia em firminópolis,inteligencia artificial em firminópolis, startflow firminópolis, agencia de inteligencia artificial em firminópolis, empresa de ia em firminópolis, empresa de inteligencia artificial em Firminópolis, automação whatsapp em firminópolis, chatbot whatsapp em firminópolis, automacao com ia em firminópolis, automacao com inteligencia artificial em firminópolis","titulo-meta":"Agência de IA em Firminópolis, GO","descricao-meta":"Transforme seu negócio com Inteligência Artificial em Firminópolis e em todo o Brasil","negocios_cidade":"1.499","negocios_estado":"171.003","populacao_estado":"7.369.156"}}}