{"page":{"id":"99ce74c8-7dd6-403c-8e4c-285280d90f83_2692","data":{"id":"7fbc78ff-e4db-4bc1-8917-2c60d077d935","uf":"MG","int":"2684","slug":"agencia-de-ia-em-caratinga-mg","cidade":"Caratinga","estado":"Minas Gerais","imagem":null,"keywords":"agência de ia em caratinga,inteligencia artificial em caratinga, startflow caratinga, agencia de inteligencia artificial em caratinga, empresa de ia em caratinga, empresa de inteligencia artificial em Caratinga, automação whatsapp em caratinga, chatbot whatsapp em caratinga, automacao com ia em caratinga, automacao com inteligencia artificial em caratinga","titulo-meta":"Agência de IA em Caratinga, MG","descricao-meta":"Transforme seu negócio com Inteligência Artificial em Caratinga e em todo o Brasil","negocios_cidade":"11.433","negocios_estado":"448.949","populacao_estado":"21.322.691"}}}