{"page":{"id":"99ce74c8-7dd6-403c-8e4c-285280d90f83_5240","data":{"id":"04db29c1-51e5-47b7-91be-5f7c040be1a2","uf":"MS","int":"5229","slug":"agencia-de-ia-em-eldorado-ms","cidade":"Eldorado","estado":"Mato Grosso do Sul","imagem":null,"keywords":"agência de ia em eldorado,inteligencia artificial em eldorado, startflow eldorado, agencia de inteligencia artificial em eldorado, empresa de ia em eldorado, empresa de inteligencia artificial em Eldorado, automação whatsapp em eldorado, chatbot whatsapp em eldorado, automacao com ia em eldorado, automacao com inteligencia artificial em eldorado","titulo-meta":"Agência de IA em Eldorado, MS","descricao-meta":"Transforme seu negócio com Inteligência Artificial em Eldorado e em todo o Brasil","negocios_cidade":"1.014","negocios_estado":"55.943","populacao_estado":"2.778.986"}}}