{"page":{"id":"99ce74c8-7dd6-403c-8e4c-285280d90f83_4221","data":{"id":"86280960-4068-4fc6-8c05-15f0fbf9c9fa","uf":"RS","int":"4211","slug":"agencia-de-ia-em-quinze-de-novembro-rs","cidade":"Quinze de Novembro","estado":"Rio Grande do Sul","imagem":null,"keywords":"agência de ia em quinze de novembro,inteligencia artificial em quinze de novembro, startflow quinze de novembro, agencia de inteligencia artificial em quinze de novembro, empresa de ia em quinze de novembro, empresa de inteligencia artificial em Quinze de Novembro, automação whatsapp em quinze de novembro, chatbot whatsapp em quinze de novembro, automacao com ia em quinze de novembro, automacao com inteligencia artificial em quinze de novembro","titulo-meta":"Agência de IA em Quinze de Novembro, RS","descricao-meta":"Transforme seu negócio com Inteligência Artificial em Quinze de Novembro e em todo o Brasil","negocios_cidade":"602","negocios_estado":"253.069","populacao_estado":"11.422.973"}}}