{"page":{"id":"99ce74c8-7dd6-403c-8e4c-285280d90f83_2739","data":{"id":"ba80e161-41b1-4cc7-88dc-02972edc2392","uf":"MG","int":"2731","slug":"agencia-de-ia-em-congonhas-mg","cidade":"Congonhas","estado":"Minas Gerais","imagem":null,"keywords":"agência de ia em congonhas,inteligencia artificial em congonhas, startflow congonhas, agencia de inteligencia artificial em congonhas, empresa de ia em congonhas, empresa de inteligencia artificial em Congonhas, automação whatsapp em congonhas, chatbot whatsapp em congonhas, automacao com ia em congonhas, automacao com inteligencia artificial em congonhas","titulo-meta":"Agência de IA em Congonhas, MG","descricao-meta":"Transforme seu negócio com Inteligência Artificial em Congonhas e em todo o Brasil","negocios_cidade":"5.758","negocios_estado":"448.949","populacao_estado":"21.322.691"}}}