{"page":{"id":"99ce74c8-7dd6-403c-8e4c-285280d90f83_2799","data":{"id":"3cd5b0d1-1610-4cb1-ae42-34632556dbca","uf":"MG","int":"2791","slug":"agencia-de-ia-em-dores-do-indaia-mg","cidade":"Dores do Indaiá","estado":"Minas Gerais","imagem":null,"keywords":"agência de ia em dores do indaiá,inteligencia artificial em dores do indaiá, startflow dores do indaiá, agencia de inteligencia artificial em dores do indaiá, empresa de ia em dores do indaiá, empresa de inteligencia artificial em Dores do Indaiá, automação whatsapp em dores do indaiá, chatbot whatsapp em dores do indaiá, automacao com ia em dores do indaiá, automacao com inteligencia artificial em dores do indaiá","titulo-meta":"Agência de IA em Dores do Indaiá, MG","descricao-meta":"Transforme seu negócio com Inteligência Artificial em Dores do Indaiá e em todo o Brasil","negocios_cidade":"1.875","negocios_estado":"448.949","populacao_estado":"21.322.691"}}}