{"page":{"id":"99ce74c8-7dd6-403c-8e4c-285280d90f83_813","data":{"id":"20216d34-fb0b-42e0-b218-265bf6ffbfcf","uf":"MA","int":"810","slug":"agencia-de-ia-em-lago-do-junco-ma","cidade":"Lago do Junco","estado":"Maranhão","imagem":null,"keywords":"agência de ia em lago do junco,inteligencia artificial em lago do junco, startflow lago do junco, agencia de inteligencia artificial em lago do junco, empresa de ia em lago do junco, empresa de inteligencia artificial em Lago do Junco, automação whatsapp em lago do junco, chatbot whatsapp em lago do junco, automacao com ia em lago do junco, automacao com inteligencia artificial em lago do junco","titulo-meta":"Agência de IA em Lago do Junco, MA","descricao-meta":"Transforme seu negócio com Inteligência Artificial em Lago do Junco e em todo o Brasil","negocios_cidade":"246","negocios_estado":"54.104","populacao_estado":"7.010.960"}}}