{"page":{"id":"99ce74c8-7dd6-403c-8e4c-285280d90f83_2415","data":{"id":"d9606143-3d7c-460a-a2db-292ed5aabd27","uf":"BA","int":"2408","slug":"agencia-de-ia-em-maracas-ba","cidade":"Maracás","estado":"Bahia","imagem":null,"keywords":"agência de ia em maracás,inteligencia artificial em maracás, startflow maracás, agencia de inteligencia artificial em maracás, empresa de ia em maracás, empresa de inteligencia artificial em Maracás, automação whatsapp em maracás, chatbot whatsapp em maracás, automacao com ia em maracás, automacao com inteligencia artificial em maracás","titulo-meta":"Agência de IA em Maracás, BA","descricao-meta":"Transforme seu negócio com Inteligência Artificial em Maracás e em todo o Brasil","negocios_cidade":"1.793","negocios_estado":"184.683","populacao_estado":"14.850.513"}}}