{"page":{"id":"99ce74c8-7dd6-403c-8e4c-285280d90f83_2324","data":{"id":"a53975ad-2490-463e-8cae-5461a7debc83","uf":"BA","int":"2317","slug":"agencia-de-ia-em-gongogi-ba","cidade":"Gongogi","estado":"Bahia","imagem":null,"keywords":"agência de ia em gongogi,inteligencia artificial em gongogi, startflow gongogi, agencia de inteligencia artificial em gongogi, empresa de ia em gongogi, empresa de inteligencia artificial em Gongogi, automação whatsapp em gongogi, chatbot whatsapp em gongogi, automacao com ia em gongogi, automacao com inteligencia artificial em gongogi","titulo-meta":"Agência de IA em Gongogi, BA","descricao-meta":"Transforme seu negócio com Inteligência Artificial em Gongogi e em todo o Brasil","negocios_cidade":"317","negocios_estado":"184.683","populacao_estado":"14.850.513"}}}