{"page":{"id":"99ce74c8-7dd6-403c-8e4c-285280d90f83_5146","data":{"id":"8252eac1-f101-4702-97fa-b5e9ccf52098","uf":"MT","int":"5135","slug":"agencia-de-ia-em-sinop-mt","cidade":"Sinop","estado":"Mato Grosso","imagem":null,"keywords":"agência de ia em sinop,inteligencia artificial em sinop, startflow sinop, agencia de inteligencia artificial em sinop, empresa de ia em sinop, empresa de inteligencia artificial em Sinop, automação whatsapp em sinop, chatbot whatsapp em sinop, automacao com ia em sinop, automacao com inteligencia artificial em sinop","titulo-meta":"Agência de IA em Sinop, MT","descricao-meta":"Transforme seu negócio com Inteligência Artificial em Sinop e em todo o Brasil","negocios_cidade":"32.001","negocios_estado":"93.905","populacao_estado":"3.701.140"}}}