{"page":{"id":"99ce74c8-7dd6-403c-8e4c-285280d90f83_574","data":{"id":"092051ba-2e26-4d80-9ef0-41e51ac283bd","uf":"PA","int":"572","slug":"agencia-de-ia-em-brejo-grande-do-araguaia-pa","cidade":"Brejo Grande do Araguaia","estado":"Pará","imagem":null,"keywords":"agência de ia em brejo grande do araguaia,inteligencia artificial em brejo grande do araguaia, startflow brejo grande do araguaia, agencia de inteligencia artificial em brejo grande do araguaia, empresa de ia em brejo grande do araguaia, empresa de inteligencia artificial em Brejo Grande do Araguaia, automação whatsapp em brejo grande do araguaia, chatbot whatsapp em brejo grande do araguaia, automacao com ia em brejo grande do araguaia, automacao com inteligencia artificial em brejo grande do araguaia","titulo-meta":"Agência de IA em Brejo Grande do Araguaia, PA","descricao-meta":"Transforme seu negócio com Inteligência Artificial em Brejo Grande do Araguaia e em todo o Brasil","negocios_cidade":"256","negocios_estado":"81.460","populacao_estado":"8.664.306"}}}