{"page":{"id":"99ce74c8-7dd6-403c-8e4c-285280d90f83_2896","data":{"id":"73b5e473-4932-4913-8edd-6b584fa17bf7","uf":"MG","int":"2887","slug":"agencia-de-ia-em-itamonte-mg","cidade":"Itamonte","estado":"Minas Gerais","imagem":null,"keywords":"agência de ia em itamonte,inteligencia artificial em itamonte, startflow itamonte, agencia de inteligencia artificial em itamonte, empresa de ia em itamonte, empresa de inteligencia artificial em Itamonte, automação whatsapp em itamonte, chatbot whatsapp em itamonte, automacao com ia em itamonte, automacao com inteligencia artificial em itamonte","titulo-meta":"Agência de IA em Itamonte, MG","descricao-meta":"Transforme seu negócio com Inteligência Artificial em Itamonte e em todo o Brasil","negocios_cidade":"2.078","negocios_estado":"448.949","populacao_estado":"21.322.691"}}}