{"page":{"id":"99ce74c8-7dd6-403c-8e4c-285280d90f83_389","data":{"id":"74c46822-e053-477b-9a60-791e1a7d3bea","uf":"PI","int":"387","slug":"agencia-de-ia-em-sao-miguel-da-baixa-grande-pi","cidade":"São Miguel da Baixa Grande","estado":"Piauí","imagem":null,"keywords":"agência de ia em são miguel da baixa grande,inteligencia artificial em são miguel da baixa grande, startflow são miguel da baixa grande, agencia de inteligencia artificial em são miguel da baixa grande, empresa de ia em são miguel da baixa grande, empresa de inteligencia artificial em São Miguel da Baixa Grande, automação whatsapp em são miguel da baixa grande, chatbot whatsapp em são miguel da baixa grande, automacao com ia em são miguel da baixa grande, automacao com inteligencia artificial em são miguel da baixa grande","titulo-meta":"Agência de IA em São Miguel da Baixa Grande, PI","descricao-meta":"Transforme seu negócio com Inteligência Artificial em São Miguel da Baixa Grande e em todo o Brasil","negocios_cidade":"115","negocios_estado":"30.745","populacao_estado":"3.375.646"}}}