{"page":{"id":"99ce74c8-7dd6-403c-8e4c-285280d90f83_700","data":{"id":"1d52284b-5759-4c73-a175-f4e434e01219","uf":"MA","int":"697","slug":"agencia-de-ia-em-alcantara-ma","cidade":"Alcântara","estado":"Maranhão","imagem":null,"keywords":"agência de ia em alcântara,inteligencia artificial em alcântara, startflow alcântara, agencia de inteligencia artificial em alcântara, empresa de ia em alcântara, empresa de inteligencia artificial em Alcântara, automação whatsapp em alcântara, chatbot whatsapp em alcântara, automacao com ia em alcântara, automacao com inteligencia artificial em alcântara","titulo-meta":"Agência de IA em Alcântara, MA","descricao-meta":"Transforme seu negócio com Inteligência Artificial em Alcântara e em todo o Brasil","negocios_cidade":"546","negocios_estado":"54.104","populacao_estado":"7.010.960"}}}