{"page":{"id":"99ce74c8-7dd6-403c-8e4c-285280d90f83_4014","data":{"id":"f1d60ff8-c361-4754-85f3-d42d6beca050","uf":"SP","int":"4005","slug":"agencia-de-ia-em-porto-feliz-sp","cidade":"Porto Feliz","estado":"São Paulo","imagem":null,"keywords":"agência de ia em porto feliz,inteligencia artificial em porto feliz, startflow porto feliz, agencia de inteligencia artificial em porto feliz, empresa de ia em porto feliz, empresa de inteligencia artificial em Porto Feliz, automação whatsapp em porto feliz, chatbot whatsapp em porto feliz, automacao com ia em porto feliz, automacao com inteligencia artificial em porto feliz","titulo-meta":"Agência de IA em Porto Feliz, SP","descricao-meta":"Transforme seu negócio com Inteligência Artificial em Porto Feliz e em todo o Brasil","negocios_cidade":"9.434","negocios_estado":"1.288.946","populacao_estado":"46.578.256"}}}