{"page":{"id":"99ce74c8-7dd6-403c-8e4c-285280d90f83_3608","data":{"id":"359bac0c-b076-46a0-b8c3-f0c196319690","uf":"MT","int":"3599","slug":"agencia-de-ia-em-sao-jose-do-povo-mt","cidade":"São José do Povo","estado":"Mato Grosso","imagem":null,"keywords":"agência de ia em são josé do povo,inteligencia artificial em são josé do povo, startflow são josé do povo, agencia de inteligencia artificial em são josé do povo, empresa de ia em são josé do povo, empresa de inteligencia artificial em São José do Povo, automação whatsapp em são josé do povo, chatbot whatsapp em são josé do povo, automacao com ia em são josé do povo, automacao com inteligencia artificial em são josé do povo","titulo-meta":"Agência de IA em São José do Povo, MT","descricao-meta":"Transforme seu negócio com Inteligência Artificial em São José do Povo e em todo o Brasil","negocios_cidade":"179","negocios_estado":"93.905","populacao_estado":"3.701.140"}}}