{"page":{"id":"99ce74c8-7dd6-403c-8e4c-285280d90f83_3392","data":{"id":"9f908a54-9a74-4f4b-8119-7f7be1ffec7c","uf":"ES","int":"3383","slug":"agencia-de-ia-em-iconha-es","cidade":"Iconha","estado":"Espírito Santo","imagem":null,"keywords":"agência de ia em iconha,inteligencia artificial em iconha, startflow iconha, agencia de inteligencia artificial em iconha, empresa de ia em iconha, empresa de inteligencia artificial em Iconha, automação whatsapp em iconha, chatbot whatsapp em iconha, automacao com ia em iconha, automacao com inteligencia artificial em iconha","titulo-meta":"Agência de IA em Iconha, ES","descricao-meta":"Transforme seu negócio com Inteligência Artificial em Iconha e em todo o Brasil","negocios_cidade":"1.896","negocios_estado":"93.963","populacao_estado":"4.102.129"}}}